{
  "hash": "1f99ab69",
  "configHash": "307b5eea",
  "lockfileHash": "9426b2e8",
  "browserHash": "4d002d45",
  "optimized": {
    "react/jsx-dev-runtime": {
      "src": "../../node_modules/react/jsx-dev-runtime.js",
      "file": "react_jsx-dev-runtime.js",
      "fileHash": "1bb156b8",
      "needsInterop": true
    },
    "react": {
      "src": "../../node_modules/react/index.js",
      "file": "react.js",
      "fileHash": "e9be09d3",
      "needsInterop": true
    },
    "react-dom/client": {
      "src": "../../node_modules/react-dom/client.js",
      "file": "react-dom_client.js",
      "fileHash": "0d7a2440",
      "needsInterop": true
    },
    "@supabase/supabase-js": {
      "src": "../../node_modules/@supabase/supabase-js/dist/index.mjs",
      "file": "@supabase_supabase-js.js",
      "fileHash": "e7b034f2",
      "needsInterop": false
    }
  },
  "chunks": {
    "chunk-62IMSUQ4": {
      "file": "chunk-62IMSUQ4.js"
    },
    "chunk-BUSYA2B4": {
      "file": "chunk-BUSYA2B4.js"
    }
  }
}